stdem/__init__.py
stdem/__main__.py
stdem/constants.py
stdem/excel_parser.py
stdem/exceptions.py
stdem/head_type.py
stdem/main.py
stdem-0.3.1.dist-info/licenses/LICENSE
stdem-0.3.1.dist-info/METADATA
stdem-0.3.1.dist-info/WHEEL
stdem-0.3.1.dist-info/entry_points.txt
stdem-0.3.1.dist-info/top_level.txt
stdem-0.3.1.dist-info/RECORD
