Metadata-Version: 2.4
Name: stdem
Version: 0.3.1
Summary: A powerful tool for converting Excel spreadsheets into JSON data with complex hierarchical structures
License-Expression: MIT
Requires-Python: >=3.12
License-File: LICENSE
Requires-Dist: openpyxl>=3.1.5
Dynamic: license-file
